moteurmapy/__init__.py
moteurmapy/helpers.py
moteurmapy/moteur_details.py
moteurmapy/moteur_list.py
moteurmapy/query_builder.py
moteurmapy/static_crawler.py
moteurmapy-1.0.4.dist-info/LICENSE
moteurmapy-1.0.4.dist-info/METADATA
moteurmapy-1.0.4.dist-info/WHEEL
moteurmapy-1.0.4.dist-info/top_level.txt
moteurmapy-1.0.4.dist-info/RECORD
