Metadata-Version: 2.1
Name: moteurmapy
Version: 1.0.4
Summary: An unofficial API for scrapping Moteur.ma
Home-page: 
Author: mouhcine
Author-email: 
License: MIT
Platform: UNKNOWN
License-File: LICENSE
Requires-Dist: fuckit
Requires-Dist: beautifulsoup4
